README.md
config.py
cursor.py
doc.py
focus.py
geom.py
menus.py
screen.py
termed.py
tests.py
utils.py
version.py
view.py
visual_line.py
visual_token.py
window.py
wm.py
dialogs/__init__.py
dialogs/button.py
dialogs/dialog.py
dialogs/file_dialog.py
dialogs/key_widget.py
dialogs/keymap_dialog.py
dialogs/prompt_dialog.py
dialogs/text_widget.py
dialogs/widget.py
dialogs/wlist.py
unittests/__init__.py
unittests/line.py
termed-1.0.3.dist-info/LICENSE
termed-1.0.3.dist-info/METADATA
termed-1.0.3.dist-info/WHEEL
termed-1.0.3.dist-info/entry_points.txt
termed-1.0.3.dist-info/top_level.txt
termed-1.0.3.dist-info/RECORD
