Metadata-Version: 2.1
Name: termed
Version: 1.0.3
Summary: A terminal based text editor
Home-page: https://github.com/amirgeva/termed
Author: Amir Geva
Author-email: amirgeva@gmail.com
License: BSD
Keywords: terminal text editor
Platform: UNKNOWN
Classifier: Development Status :: 3 - Alpha
Classifier: Intended Audience :: Developers
Classifier: Topic :: Text Editors
Classifier: License :: OSI Approved :: BSD License
Classifier: Programming Language :: Python :: 3
Classifier: Programming Language :: Python :: 3.3
Classifier: Programming Language :: Python :: 3.4
Classifier: Programming Language :: Python :: 3.5
Classifier: Programming Language :: Python :: 3.6
Requires-Dist: pyperclip
Requires-Dist: termcolor
